FFFLaTeX/FFFparser.py
FFFLaTeX/__init__.py
FFFLaTeX/configLaTeX.py
FFFLaTeX/configSymbols.py
FFFLaTeX/parserutil.py
FFFLaTeX-1.6.2.dist-info/LICENSE
FFFLaTeX-1.6.2.dist-info/METADATA
FFFLaTeX-1.6.2.dist-info/WHEEL
FFFLaTeX-1.6.2.dist-info/entry_points.txt
FFFLaTeX-1.6.2.dist-info/top_level.txt
FFFLaTeX-1.6.2.dist-info/RECORD
