Metadata-Version: 2.1
Name: FFFLaTeX
Version: 1.6.2
Summary: Small scrapper script generating a basic LaTeX article from any FFF blog post. Includes images, videos and tables in the final pdf upon compilation. Compilation on windows will require to install wget on windows. 
Home-page: https://github.com/helldragger/FactorioFridayFactsLaTeX
Author: Helldragger
Author-email: chritopher1223334444@gmail.com
License: lGPL v3
Keywords: Factorio LaTeX
Platform: UNKNOWN
Classifier: Programming Language :: Python :: 3.6
Classifier: Programming Language :: Python :: 3
Classifier: License :: OSI Approved :: GNU Lesser General Public License v3 or later (LGPLv3+)
Classifier: Programming Language :: Python :: Implementation :: CPython
Classifier: Topic :: Utilities
Classifier: Operating System :: OS Independent
Requires-Dist: beautifulsoup4
Requires-Dist: urllib3
Requires-Dist: html5lib
